VerilogBeispiele/Halbaddierer.v
module Halbaddierer 
        (
            input summand1,
            input summand2,
            
            output summe,
            output uebertrag
        );
    assign uebertrag = summand1 & summand2;
    assign summe = summand1 ^ summand2;
endmodule

VerilogBeispiele/Volladdierer.v
`include "Halbaddierer.v"

module Volladdierer
        (
            input summand1,
            input summand2,
            input summand3,

            output summe,
            output uebertrag
        );
    wire summe1;
    wire uebertrag1;
    wire uebertrag2;
    assign uebertrag = uebertrag1 | uebertrag2;
    Halbaddierer hb1 (summand1, summand2, summe1, uebertrag1);
    Halbaddierer hb2 (summe1, summand3, summe, uebertrag2);
endmodule

VerilogBeispiele/VolladdiererTest.v
`include "Volladdierer.v"
module VolladdiererTest ();
    reg s1, s2, s3;
    wire uebertrag, summe;

    Volladdierer va(s1, s2, s3, summe, uebertrag);

    initial begin 
        $dumpfile("test.vcd");
        $dumpvars(0, VolladdiererTest);
        s1 = 0; s2 = 0; s3 = 0;
        #10
        s1 = 0; s2 = 0; s3 = 1;
        #10
        s1 = 0; s2 = 1; s3 = 0;
        #10
        s1 = 0; s2 = 1; s3 = 1;
        #10
        s1 = 1; s2 = 0; s3 = 0;
        #10
        s1 = 1; s2 = 0; s3 = 1;
        #10
        s1 = 1; s2 = 1; s3 = 0;
        #10
        s1 = 1; s2 = 1; s3 = 1;
        #10
        $finish;


    end
endmodule

VerilogBeispiele/test.vcd
$date
	Fri Mar 17 21:02:28 2023
$end
$version
	Icarus Verilog
$end
$timescale
	1s
$end
$scope module VolladdiererTest $end
$var wire 1 ! uebertrag $end
$var wire 1 " summe $end
$var reg 1 # s1 $end
$var reg 1 $ s2 $end
$var reg 1 % s3 $end
$scope module va $end
$var wire 1 # summand1 $end
$var wire 1 $ summand2 $end
$var wire 1 % summand3 $end
$var wire 1 ! uebertrag $end
$var wire 1 & uebertrag2 $end
$var wire 1 ' uebertrag1 $end
$var wire 1 ( summe1 $end
$var wire 1 " summe $end
$scope module hb1 $end
$var wire 1 # summand1 $end
$var wire 1 $ summand2 $end
$var wire 1 ( summe $end
$var wire 1 ' uebertrag $end
$upscope $end
$scope module hb2 $end
$var wire 1 ( summand1 $end
$var wire 1 % summand2 $end
$var wire 1 " summe $end
$var wire 1 & uebertrag $end
$upscope $end
$upscope $end
$upscope $end
$enddefinitions $end
$comment Show the parameter values. $end
$dumpall
$end
#0
$dumpvars
0(
0'
0&
0%
0$
0#
0"
0!
$end
#10
1"
1%
#20
1(
0%
1$
#30
1!
1&
0"
1%
#40
0!
0&
1"
0%
0$
1#
#50
1!
1&
0"
1%
#60
0&
1'
0(
0%
1$
#70
1"
1%
